{"currency":"USD","datetime":"2022-10-05T14:54:51.000Z","id":21719,"payee_acc_id":3109,"payer_acc_id":110021,"txn_amt":222.27,"txn_type":3}
{"currency":"USD","datetime":"2022-12-09T20:08:12.000Z","id":21722,"payee_acc_id":3346,"payer_acc_id":110027,"txn_amt":188.49,"txn_type":4}
{"currency":"USD","datetime":"2022-04-19T09:54:27.000Z","id":21723,"payee_acc_id":1191,"payer_acc_id":110028,"txn_amt":242.23,"txn_type":5}
{"currency":"USD","datetime":"2022-04-30T00:00:49.000Z","id":21728,"payee_acc_id":1368,"payer_acc_id":110035,"txn_amt":178.27,"txn_type":4}
{"currency":"USD","datetime":"2022-08-04T09:29:21.000Z","id":21735,"payee_acc_id":9870,"payer_acc_id":110043,"txn_amt":260.06,"txn_type":2}
{"currency":"USD","datetime":"2022-02-20T07:34:00.000Z","id":21741,"payee_acc_id":4038,"payer_acc_id":110055,"txn_amt":240.54,"txn_type":3}
{"currency":"USD","datetime":"2022-11-05T14:06:16.000Z","id":21745,"payee_acc_id":3886,"payer_acc_id":110060,"txn_amt":302.22,"txn_type":1}
{"currency":"USD","datetime":"2022-08-01T22:22:48.000Z","id":21754,"payee_acc_id":2171,"payer_acc_id":110079,"txn_amt":204.17,"txn_type":3}
{"currency":"USD","datetime":"2022-10-25T23:48:33.000Z","id":21756,"payee_acc_id":1275,"payer_acc_id":110083,"txn_amt":264.44,"txn_type":2}
{"currency":"USD","datetime":"2022-08-25T21:35:02.000Z","id":21767,"payee_acc_id":1204,"payer_acc_id":110103,"txn_amt":193.68,"txn_type":3}
{"currency":"USD","datetime":"2022-11-26T04:22:31.000Z","id":21770,"payee_acc_id":1341,"payer_acc_id":110106,"txn_amt":151.72,"txn_type":5}
{"currency":"USD","datetime":"2022-05-21T22:01:04.000Z","id":21772,"payee_acc_id":6481,"payer_acc_id":110110,"txn_amt":180.13,"txn_type":1}
{"currency":"USD","datetime":"2022-02-06T19:26:17.000Z","id":21775,"payee_acc_id":4733,"payer_acc_id":110115,"txn_amt":169.83,"txn_type":5}
{"currency":"USD","datetime":"2022-06-16T14:03:18.000Z","id":21783,"payee_acc_id":4329,"payer_acc_id":110127,"txn_amt":174.12,"txn_type":5}
{"currency":"USD","datetime":"2022-02-23T04:38:10.000Z","id":21785,"payee_acc_id":1248,"payer_acc_id":110131,"txn_amt":324.98,"txn_type":1}
{"currency":"USD","datetime":"2022-03-29T12:35:46.000Z","id":21786,"payee_acc_id":9424,"payer_acc_id":110136,"txn_amt":218.97,"txn_type":4}
{"currency":"USD","datetime":"2022-03-07T03:58:22.000Z","id":21790,"payee_acc_id":8711,"payer_acc_id":110140,"txn_amt":221.26,"txn_type":1}
{"currency":"USD","datetime":"2022-12-26T23:25:25.000Z","id":21796,"payee_acc_id":43653,"payer_acc_id":110148,"txn_amt":221.4,"txn_type":1}
{"currency":"USD","datetime":"2022-11-19T21:26:20.000Z","id":21798,"payee_acc_id":4600,"payer_acc_id":110153,"txn_amt":168.79,"txn_type":5}
{"currency":"USD","datetime":"2022-06-03T06:55:00.000Z","id":21800,"payee_acc_id":1569,"payer_acc_id":110157,"txn_amt":309.53,"txn_type":1}
{"currency":"USD","datetime":"2022-05-16T00:47:06.000Z","id":21805,"payee_acc_id":2349,"payer_acc_id":110165,"txn_amt":166.46,"txn_type":3}
{"currency":"USD","datetime":"2022-11-25T00:51:16.000Z","id":21818,"payee_acc_id":71135,"payer_acc_id":110191,"txn_amt":86.59,"txn_type":4}
{"currency":"USD","datetime":"2022-04-24T11:25:11.000Z","id":21831,"payee_acc_id":5067,"payer_acc_id":110218,"txn_amt":278.56,"txn_type":2}
{"currency":"USD","datetime":"2022-03-07T11:38:44.000Z","id":21832,"payee_acc_id":4030,"payer_acc_id":110218,"txn_amt":223.35,"txn_type":4}
{"currency":"USD","datetime":"2022-02-23T23:18:40.000Z","id":21835,"payee_acc_id":86526,"payer_acc_id":110222,"txn_amt":182.1,"txn_type":5}
{"currency":"USD","datetime":"2022-11-11T07:47:01.000Z","id":21837,"payee_acc_id":6272,"payer_acc_id":110223,"txn_amt":187.35,"txn_type":3}
{"currency":"USD","datetime":"2022-03-02T16:48:41.000Z","id":21838,"payee_acc_id":4439,"payer_acc_id":110224,"txn_amt":169.48,"txn_type":5}
{"currency":"USD","datetime":"2022-02-28T04:11:23.000Z","id":21855,"payee_acc_id":1399,"payer_acc_id":110261,"txn_amt":259.77,"txn_type":2}
{"currency":"USD","datetime":"2022-12-07T22:27:03.000Z","id":21857,"payee_acc_id":4035,"payer_acc_id":110265,"txn_amt":187.88,"txn_type":1}
{"currency":"USD","datetime":"2022-11-22T10:07:16.000Z","id":21858,"payee_acc_id":4915,"payer_acc_id":110266,"txn_amt":187.01,"txn_type":5}
{"currency":"USD","datetime":"2022-06-06T10:38:06.000Z","id":21861,"payee_acc_id":1255,"payer_acc_id":110274,"txn_amt":239.13,"txn_type":3}
{"currency":"USD","datetime":"2022-07-01T15:58:35.000Z","id":21865,"payee_acc_id":5095,"payer_acc_id":110280,"txn_amt":184.78,"txn_type":5}
{"currency":"USD","datetime":"2022-04-30T02:42:14.000Z","id":21867,"payee_acc_id":3471,"payer_acc_id":110283,"txn_amt":246.15,"txn_type":3}
{"currency":"USD","datetime":"2022-12-08T13:27:51.000Z","id":21869,"payee_acc_id":5606,"payer_acc_id":110285,"txn_amt":257.25,"txn_type":5}
{"currency":"USD","datetime":"2022-09-10T12:30:46.000Z","id":21891,"payee_acc_id":3423,"payer_acc_id":110311,"txn_amt":183.83,"txn_type":1}
{"currency":"USD","datetime":"2022-08-05T13:00:27.000Z","id":21892,"payee_acc_id":1816,"payer_acc_id":110312,"txn_amt":174.53,"txn_type":4}
{"currency":"USD","datetime":"2022-04-05T17:54:24.000Z","id":21894,"payee_acc_id":4383,"payer_acc_id":110318,"txn_amt":233.94,"txn_type":4}
{"currency":"USD","datetime":"2022-05-22T20:49:18.000Z","id":21904,"payee_acc_id":5988,"payer_acc_id":110332,"txn_amt":174.44,"txn_type":3}
{"currency":"USD","datetime":"2022-12-25T20:31:01.000Z","id":21909,"payee_acc_id":7113,"payer_acc_id":110338,"txn_amt":272.25,"txn_type":4}
{"currency":"USD","datetime":"2022-02-28T00:07:31.000Z","id":21911,"payee_acc_id":9042,"payer_acc_id":110340,"txn_amt":186.39,"txn_type":1}
{"currency":"USD","datetime":"2022-09-07T16:15:30.000Z","id":21917,"payee_acc_id":39999,"payer_acc_id":110352,"txn_amt":179.9,"txn_type":5}
{"currency":"USD","datetime":"2022-06-23T16:21:45.000Z","id":21921,"payee_acc_id":2346,"payer_acc_id":110359,"txn_amt":261.79,"txn_type":5}
{"currency":"USD","datetime":"2022-01-02T03:19:29.000Z","id":21923,"payee_acc_id":34473,"payer_acc_id":110362,"txn_amt":162.0,"txn_type":5}
{"currency":"USD","datetime":"2022-11-07T10:25:46.000Z","id":21928,"payee_acc_id":6173,"payer_acc_id":110371,"txn_amt":163.52,"txn_type":5}
{"currency":"USD","datetime":"2022-03-15T23:34:23.000Z","id":21934,"payee_acc_id":2338,"payer_acc_id":110383,"txn_amt":175.66,"txn_type":2}
{"currency":"USD","datetime":"2022-01-25T09:18:43.000Z","id":21935,"payee_acc_id":1734,"payer_acc_id":110390,"txn_amt":267.18,"txn_type":2}
{"currency":"USD","datetime":"2022-09-01T04:00:57.000Z","id":21942,"payee_acc_id":3471,"payer_acc_id":110401,"txn_amt":189.94,"txn_type":4}
{"currency":"USD","datetime":"2022-09-26T02:23:38.000Z","id":21945,"payee_acc_id":3423,"payer_acc_id":110407,"txn_amt":177.25,"txn_type":3}
{"currency":"USD","datetime":"2022-08-17T23:32:46.000Z","id":21948,"payee_acc_id":1673,"payer_acc_id":110416,"txn_amt":148.22,"txn_type":5}
{"currency":"USD","datetime":"2022-04-23T09:08:50.000Z","id":21952,"payee_acc_id":1021,"payer_acc_id":110421,"txn_amt":140.62,"txn_type":4}
{"currency":"USD","datetime":"2022-10-27T09:38:07.000Z","id":21955,"payee_acc_id":6159,"payer_acc_id":110426,"txn_amt":185.67,"txn_type":3}
{"currency":"USD","datetime":"2022-08-19T01:09:38.000Z","id":21960,"payee_acc_id":6690,"payer_acc_id":110433,"txn_amt":127.02,"txn_type":1}
{"currency":"USD","datetime":"2022-10-13T16:11:59.000Z","id":21962,"payee_acc_id":3278,"payer_acc_id":110436,"txn_amt":252.32,"txn_type":3}
{"currency":"USD","datetime":"2022-06-23T05:59:26.000Z","id":21972,"payee_acc_id":1008,"payer_acc_id":110452,"txn_amt":218.55,"txn_type":4}
{"currency":"USD","datetime":"2022-10-29T04:34:53.000Z","id":21990,"payee_acc_id":52516,"payer_acc_id":110477,"txn_amt":186.5,"txn_type":3}
{"currency":"USD","datetime":"2022-07-25T04:41:43.000Z","id":21999,"payee_acc_id":9475,"payer_acc_id":110492,"txn_amt":180.79,"txn_type":4}
{"currency":"USD","datetime":"2022-03-11T17:19:44.000Z","id":22021,"payee_acc_id":33396,"payer_acc_id":110526,"txn_amt":158.6,"txn_type":3}
{"currency":"USD","datetime":"2022-09-15T16:59:12.000Z","id":22029,"payee_acc_id":5540,"payer_acc_id":110536,"txn_amt":184.26,"txn_type":5}
{"currency":"USD","datetime":"2022-11-30T14:41:39.000Z","id":22034,"payee_acc_id":3961,"payer_acc_id":110544,"txn_amt":185.68,"txn_type":2}
{"currency":"USD","datetime":"2022-01-10T04:51:27.000Z","id":22035,"payee_acc_id":2452,"payer_acc_id":110545,"txn_amt":136.58,"txn_type":2}
{"currency":"USD","datetime":"2022-09-14T00:42:44.000Z","id":22042,"payee_acc_id":5217,"payer_acc_id":110552,"txn_amt":144.02,"txn_type":2}
{"currency":"USD","datetime":"2022-06-29T10:24:41.000Z","id":22046,"payee_acc_id":6750,"payer_acc_id":110565,"txn_amt":262.08,"txn_type":1}
{"currency":"USD","datetime":"2022-07-30T00:37:02.000Z","id":2205,"payee_acc_id":135978,"payer_acc_id":79480,"txn_amt":215.83,"txn_type":4}
{"currency":"USD","datetime":"2022-10-10T01:35:38.000Z","id":22051,"payee_acc_id":6300,"payer_acc_id":110572,"txn_amt":304.25,"txn_type":2}
{"currency":"USD","datetime":"2022-10-01T06:17:33.000Z","id":22054,"payee_acc_id":1126,"payer_acc_id":110575,"txn_amt":153.33,"txn_type":3}
{"currency":"USD","datetime":"2022-05-19T10:37:36.000Z","id":22055,"payee_acc_id":8651,"payer_acc_id":110578,"txn_amt":236.22,"txn_type":5}
{"currency":"USD","datetime":"2022-04-04T12:22:55.000Z","id":22064,"payee_acc_id":3009,"payer_acc_id":110594,"txn_amt":138.89,"txn_type":1}
{"currency":"USD","datetime":"2022-03-15T15:47:49.000Z","id":22073,"payee_acc_id":3471,"payer_acc_id":110609,"txn_amt":223.26,"txn_type":3}
{"currency":"USD","datetime":"2022-04-24T07:39:31.000Z","id":22083,"payee_acc_id":5559,"payer_acc_id":110624,"txn_amt":109.93,"txn_type":3}
{"currency":"USD","datetime":"2022-06-09T10:11:13.000Z","id":22095,"payee_acc_id":1317,"payer_acc_id":110644,"txn_amt":272.88,"txn_type":2}
{"currency":"USD","datetime":"2022-10-20T17:05:25.000Z","id":22099,"payee_acc_id":3562,"payer_acc_id":110649,"txn_amt":215.13,"txn_type":1}
{"currency":"USD","datetime":"2022-05-08T22:44:53.000Z","id":22102,"payee_acc_id":27682,"payer_acc_id":110658,"txn_amt":167.9,"txn_type":3}
{"currency":"USD","datetime":"2022-07-12T16:46:08.000Z","id":22107,"payee_acc_id":1072,"payer_acc_id":110666,"txn_amt":238.25,"txn_type":4}
{"currency":"USD","datetime":"2022-12-09T03:58:09.000Z","id":22110,"payee_acc_id":7349,"payer_acc_id":110670,"txn_amt":247.21,"txn_type":1}
{"currency":"USD","datetime":"2022-10-17T18:32:54.000Z","id":22118,"payee_acc_id":5763,"payer_acc_id":110689,"txn_amt":194.79,"txn_type":3}
{"currency":"USD","datetime":"2022-08-05T03:05:41.000Z","id":22120,"payee_acc_id":8591,"payer_acc_id":110693,"txn_amt":228.85,"txn_type":5}
{"currency":"USD","datetime":"2022-01-20T03:05:36.000Z","id":22121,"payee_acc_id":1003,"payer_acc_id":110694,"txn_amt":180.32,"txn_type":5}
{"currency":"USD","datetime":"2022-06-28T21:15:33.000Z","id":22134,"payee_acc_id":1396,"payer_acc_id":110713,"txn_amt":275.97,"txn_type":1}
{"currency":"USD","datetime":"2022-08-20T22:45:54.000Z","id":22138,"payee_acc_id":6064,"payer_acc_id":110718,"txn_amt":227.34,"txn_type":1}
{"currency":"USD","datetime":"2022-04-14T23:30:26.000Z","id":22144,"payee_acc_id":7805,"payer_acc_id":110726,"txn_amt":185.13,"txn_type":4}
{"currency":"USD","datetime":"2022-02-06T17:35:55.000Z","id":22145,"payee_acc_id":6253,"payer_acc_id":110728,"txn_amt":172.47,"txn_type":2}
{"currency":"USD","datetime":"2022-03-31T08:23:48.000Z","id":22147,"payee_acc_id":56300,"payer_acc_id":110729,"txn_amt":243.1,"txn_type":5}
{"currency":"USD","datetime":"2022-05-09T04:41:31.000Z","id":22151,"payee_acc_id":9485,"payer_acc_id":110734,"txn_amt":210.82,"txn_type":5}
{"currency":"USD","datetime":"2022-01-24T12:23:52.000Z","id":22153,"payee_acc_id":11596,"payer_acc_id":110736,"txn_amt":83.02,"txn_type":1}
{"currency":"USD","datetime":"2022-08-21T05:24:29.000Z","id":22156,"payee_acc_id":3518,"payer_acc_id":110741,"txn_amt":201.18,"txn_type":3}
{"currency":"USD","datetime":"2022-02-09T01:51:54.000Z","id":22165,"payee_acc_id":1349,"payer_acc_id":110755,"txn_amt":123.79,"txn_type":1}
{"currency":"USD","datetime":"2022-03-27T15:58:51.000Z","id":22166,"payee_acc_id":8181,"payer_acc_id":110757,"txn_amt":217.39,"txn_type":1}
{"currency":"USD","datetime":"2022-03-09T19:40:48.000Z","id":22169,"payee_acc_id":8433,"payer_acc_id":110760,"txn_amt":235.42,"txn_type":1}
{"currency":"USD","datetime":"2022-06-06T10:40:36.000Z","id":22172,"payee_acc_id":1791,"payer_acc_id":110768,"txn_amt":216.43,"txn_type":5}
{"currency":"USD","datetime":"2022-03-11T02:25:33.000Z","id":22173,"payee_acc_id":4943,"payer_acc_id":110768,"txn_amt":222.66,"txn_type":2}
{"currency":"USD","datetime":"2022-11-02T13:56:46.000Z","id":22174,"payee_acc_id":5275,"payer_acc_id":110768,"txn_amt":233.18,"txn_type":4}
{"currency":"USD","datetime":"2022-05-19T05:31:14.000Z","id":22175,"payee_acc_id":21993,"payer_acc_id":110769,"txn_amt":193.6,"txn_type":5}
{"currency":"USD","datetime":"2022-09-29T14:07:55.000Z","id":22176,"payee_acc_id":81975,"payer_acc_id":110772,"txn_amt":290.2,"txn_type":1}
{"currency":"USD","datetime":"2022-02-03T23:30:36.000Z","id":22179,"payee_acc_id":2499,"payer_acc_id":110777,"txn_amt":207.16,"txn_type":1}
{"currency":"USD","datetime":"2022-01-23T17:43:53.000Z","id":22185,"payee_acc_id":40234,"payer_acc_id":110783,"txn_amt":229.9,"txn_type":4}
{"currency":"USD","datetime":"2022-04-19T11:16:15.000Z","id":22188,"payee_acc_id":27596,"payer_acc_id":110787,"txn_amt":181.8,"txn_type":1}
{"currency":"USD","datetime":"2022-02-10T05:32:00.000Z","id":22192,"payee_acc_id":1771,"payer_acc_id":110790,"txn_amt":156.94,"txn_type":4}
{"currency":"USD","datetime":"2022-01-09T23:22:48.000Z","id":22203,"payee_acc_id":9841,"payer_acc_id":110804,"txn_amt":227.86,"txn_type":3}
{"currency":"USD","datetime":"2022-08-20T04:31:12.000Z","id":22211,"payee_acc_id":2171,"payer_acc_id":110823,"txn_amt":195.63,"txn_type":1}
{"currency":"USD","datetime":"2022-03-26T18:24:06.000Z","id":22224,"payee_acc_id":2400,"payer_acc_id":110860,"txn_amt":209.59,"txn_type":1}
{"currency":"USD","datetime":"2022-06-03T18:33:41.000Z","id":22237,"payee_acc_id":1076,"payer_acc_id":110881,"txn_amt":219.74,"txn_type":2}
{"currency":"USD","datetime":"2022-09-05T03:03:13.000Z","id":22238,"payee_acc_id":3948,"payer_acc_id":110885,"txn_amt":219.88,"txn_type":1}
{"currency":"USD","datetime":"2022-05-07T08:12:07.000Z","id":22249,"payee_acc_id":8070,"payer_acc_id":110907,"txn_amt":130.48,"txn_type":3}
{"currency":"USD","datetime":"2022-06-21T08:14:07.000Z","id":22253,"payee_acc_id":6224,"payer_acc_id":110915,"txn_amt":115.56,"txn_type":5}
{"currency":"USD","datetime":"2022-03-23T09:56:50.000Z","id":22254,"payee_acc_id":7470,"payer_acc_id":110922,"txn_amt":133.49,"txn_type":5}
{"currency":"USD","datetime":"2022-10-06T07:33:15.000Z","id":22255,"payee_acc_id":2990,"payer_acc_id":110925,"txn_amt":175.73,"txn_type":2}
{"currency":"USD","datetime":"2022-07-29T17:12:35.000Z","id":22258,"payee_acc_id":1673,"payer_acc_id":110928,"txn_amt":181.16,"txn_type":5}
{"currency":"USD","datetime":"2022-07-12T10:37:54.000Z","id":22260,"payee_acc_id":7556,"payer_acc_id":110932,"txn_amt":228.67,"txn_type":3}
{"currency":"USD","datetime":"2022-08-27T02:39:02.000Z","id":22267,"payee_acc_id":1489,"payer_acc_id":110943,"txn_amt":206.06,"txn_type":1}
{"currency":"USD","datetime":"2022-10-21T16:53:52.000Z","id":22272,"payee_acc_id":4350,"payer_acc_id":110948,"txn_amt":168.46,"txn_type":3}
{"currency":"USD","datetime":"2022-06-25T11:18:27.000Z","id":22277,"payee_acc_id":4506,"payer_acc_id":110954,"txn_amt":204.76,"txn_type":5}
{"currency":"USD","datetime":"2022-10-20T20:51:03.000Z","id":22283,"payee_acc_id":1726,"payer_acc_id":110963,"txn_amt":153.14,"txn_type":5}
{"currency":"USD","datetime":"2022-03-02T16:29:11.000Z","id":22288,"payee_acc_id":11589,"payer_acc_id":110973,"txn_amt":147.6,"txn_type":3}
{"currency":"USD","datetime":"2022-09-07T08:03:44.000Z","id":22291,"payee_acc_id":46483,"payer_acc_id":110984,"txn_amt":172.1,"txn_type":5}
{"currency":"USD","datetime":"2022-02-05T06:36:28.000Z","id":22296,"payee_acc_id":4172,"payer_acc_id":110995,"txn_amt":207.11,"txn_type":3}
{"currency":"USD","datetime":"2022-11-23T05:32:01.000Z","id":22297,"payee_acc_id":1719,"payer_acc_id":110996,"txn_amt":196.35,"txn_type":5}
{"currency":"USD","datetime":"2022-08-12T22:29:18.000Z","id":22303,"payee_acc_id":1321,"payer_acc_id":111010,"txn_amt":228.49,"txn_type":4}
{"currency":"USD","datetime":"2022-05-17T00:21:56.000Z","id":22309,"payee_acc_id":7994,"payer_acc_id":111020,"txn_amt":119.24,"txn_type":1}
{"currency":"USD","datetime":"2022-04-14T18:34:25.000Z","id":22310,"payee_acc_id":3482,"payer_acc_id":111021,"txn_amt":172.17,"txn_type":1}
{"currency":"USD","datetime":"2022-09-17T23:43:09.000Z","id":22327,"payee_acc_id":20355,"payer_acc_id":111056,"txn_amt":184.0,"txn_type":2}
{"currency":"USD","datetime":"2022-09-24T23:42:40.000Z","id":22329,"payee_acc_id":9452,"payer_acc_id":111057,"txn_amt":255.31,"txn_type":1}
{"currency":"USD","datetime":"2022-03-05T13:20:13.000Z","id":22330,"payee_acc_id":38259,"payer_acc_id":111059,"txn_amt":135.0,"txn_type":1}
{"currency":"USD","datetime":"2022-02-05T16:20:15.000Z","id":22332,"payee_acc_id":3151,"payer_acc_id":111064,"txn_amt":273.96,"txn_type":4}
{"currency":"USD","datetime":"2022-04-04T07:36:14.000Z","id":22333,"payee_acc_id":6342,"payer_acc_id":111064,"txn_amt":224.49,"txn_type":5}
{"currency":"USD","datetime":"2022-10-16T07:32:43.000Z","id":22334,"payee_acc_id":5406,"payer_acc_id":111066,"txn_amt":291.81,"txn_type":1}
{"currency":"USD","datetime":"2022-11-22T11:36:31.000Z","id":22335,"payee_acc_id":1662,"payer_acc_id":111069,"txn_amt":318.59,"txn_type":4}
{"currency":"USD","datetime":"2022-06-07T23:51:03.000Z","id":22341,"payee_acc_id":3227,"payer_acc_id":111075,"txn_amt":238.65,"txn_type":3}
{"currency":"USD","datetime":"2022-06-05T15:02:21.000Z","id":22347,"payee_acc_id":1135,"payer_acc_id":111087,"txn_amt":228.14,"txn_type":5}
{"currency":"USD","datetime":"2022-10-25T22:37:41.000Z","id":22352,"payee_acc_id":89230,"payer_acc_id":111098,"txn_amt":240.1,"txn_type":1}
{"currency":"USD","datetime":"2022-11-21T00:09:31.000Z","id":22353,"payee_acc_id":4575,"payer_acc_id":111099,"txn_amt":193.24,"txn_type":3}
{"currency":"USD","datetime":"2022-05-26T05:54:16.000Z","id":22354,"payee_acc_id":3602,"payer_acc_id":111100,"txn_amt":238.98,"txn_type":2}
{"currency":"USD","datetime":"2022-08-27T21:41:27.000Z","id":22355,"payee_acc_id":5249,"payer_acc_id":111101,"txn_amt":151.94,"txn_type":4}
{"currency":"USD","datetime":"2022-03-22T02:01:38.000Z","id":22356,"payee_acc_id":2994,"payer_acc_id":111102,"txn_amt":181.09,"txn_type":3}
{"currency":"USD","datetime":"2022-12-25T20:35:30.000Z","id":22361,"payee_acc_id":2242,"payer_acc_id":111113,"txn_amt":167.76,"txn_type":4}
{"currency":"USD","datetime":"2022-07-27T02:52:40.000Z","id":22365,"payee_acc_id":9656,"payer_acc_id":111125,"txn_amt":131.71,"txn_type":1}
{"currency":"USD","datetime":"2022-12-10T03:06:07.000Z","id":22374,"payee_acc_id":6460,"payer_acc_id":111143,"txn_amt":319.01,"txn_type":5}
{"currency":"USD","datetime":"2022-07-16T16:47:40.000Z","id":22382,"payee_acc_id":12959,"payer_acc_id":111156,"txn_amt":95.92,"txn_type":2}
{"currency":"USD","datetime":"2022-10-28T18:05:36.000Z","id":22387,"payee_acc_id":13972,"payer_acc_id":111169,"txn_amt":290.8,"txn_type":5}
{"currency":"USD","datetime":"2022-05-25T17:16:48.000Z","id":22394,"payee_acc_id":1637,"payer_acc_id":111177,"txn_amt":139.95,"txn_type":1}
{"currency":"USD","datetime":"2022-05-31T18:46:47.000Z","id":22397,"payee_acc_id":56060,"payer_acc_id":111184,"txn_amt":91.53,"txn_type":5}
{"currency":"USD","datetime":"2022-10-07T14:05:47.000Z","id":22404,"payee_acc_id":3666,"payer_acc_id":111193,"txn_amt":159.22,"txn_type":3}
{"currency":"USD","datetime":"2022-07-26T02:18:50.000Z","id":22406,"payee_acc_id":1210,"payer_acc_id":111195,"txn_amt":149.94,"txn_type":1}
{"currency":"USD","datetime":"2022-01-23T07:23:34.000Z","id":22407,"payee_acc_id":52375,"payer_acc_id":111196,"txn_amt":177.1,"txn_type":4}
{"currency":"USD","datetime":"2022-08-10T12:29:13.000Z","id":22410,"payee_acc_id":2429,"payer_acc_id":111200,"txn_amt":233.84,"txn_type":3}
{"currency":"USD","datetime":"2022-12-27T19:22:28.000Z","id":22415,"payee_acc_id":4501,"payer_acc_id":111208,"txn_amt":171.11,"txn_type":5}
{"currency":"USD","datetime":"2022-03-14T18:16:05.000Z","id":22416,"payee_acc_id":1263,"payer_acc_id":111209,"txn_amt":176.99,"txn_type":2}
{"currency":"USD","datetime":"2022-10-26T22:27:43.000Z","id":22428,"payee_acc_id":45128,"payer_acc_id":111230,"txn_amt":282.1,"txn_type":4}
{"currency":"USD","datetime":"2022-02-15T21:39:59.000Z","id":22436,"payee_acc_id":84429,"payer_acc_id":111247,"txn_amt":159.5,"txn_type":5}
{"currency":"USD","datetime":"2022-04-16T11:28:48.000Z","id":22439,"payee_acc_id":67989,"payer_acc_id":111253,"txn_amt":169.6,"txn_type":2}
{"currency":"USD","datetime":"2022-03-09T15:21:03.000Z","id":22441,"payee_acc_id":5784,"payer_acc_id":111260,"txn_amt":213.52,"txn_type":2}
{"currency":"USD","datetime":"2022-06-25T22:09:41.000Z","id":22446,"payee_acc_id":51061,"payer_acc_id":111278,"txn_amt":243.9,"txn_type":1}
{"currency":"USD","datetime":"2022-05-26T06:34:13.000Z","id":22455,"payee_acc_id":6403,"payer_acc_id":111294,"txn_amt":206.37,"txn_type":5}
{"currency":"USD","datetime":"2022-12-23T19:21:15.000Z","id":22457,"payee_acc_id":3084,"payer_acc_id":111295,"txn_amt":218.26,"txn_type":1}
{"currency":"USD","datetime":"2022-03-15T01:55:13.000Z","id":22460,"payee_acc_id":2750,"payer_acc_id":111298,"txn_amt":258.49,"txn_type":4}
{"currency":"USD","datetime":"2022-05-15T23:04:55.000Z","id":22462,"payee_acc_id":4147,"payer_acc_id":111300,"txn_amt":207.67,"txn_type":4}
{"currency":"USD","datetime":"2022-11-19T21:25:56.000Z","id":22465,"payee_acc_id":2295,"payer_acc_id":111310,"txn_amt":321.17,"txn_type":1}
{"currency":"USD","datetime":"2022-04-12T16:44:51.000Z","id":22472,"payee_acc_id":7779,"payer_acc_id":111321,"txn_amt":264.31,"txn_type":5}
{"currency":"USD","datetime":"2022-08-02T20:27:32.000Z","id":22474,"payee_acc_id":1350,"payer_acc_id":111327,"txn_amt":179.98,"txn_type":3}
{"currency":"USD","datetime":"2022-08-05T16:57:46.000Z","id":22478,"payee_acc_id":1331,"payer_acc_id":111332,"txn_amt":321.55,"txn_type":2}
{"currency":"USD","datetime":"2022-08-07T15:55:35.000Z","id":22482,"payee_acc_id":1911,"payer_acc_id":111336,"txn_amt":167.29,"txn_type":4}
{"currency":"USD","datetime":"2022-09-11T21:30:49.000Z","id":22485,"payee_acc_id":1269,"payer_acc_id":111343,"txn_amt":150.14,"txn_type":5}
{"currency":"USD","datetime":"2022-03-17T20:32:17.000Z","id":22488,"payee_acc_id":2818,"payer_acc_id":111344,"txn_amt":191.12,"txn_type":5}
{"currency":"USD","datetime":"2022-05-27T04:40:29.000Z","id":22489,"payee_acc_id":1700,"payer_acc_id":111347,"txn_amt":130.48,"txn_type":5}
{"currency":"USD","datetime":"2022-03-22T13:29:17.000Z","id":22495,"payee_acc_id":7953,"payer_acc_id":111363,"txn_amt":143.48,"txn_type":5}
{"currency":"USD","datetime":"2022-11-01T08:42:12.000Z","id":22498,"payee_acc_id":2400,"payer_acc_id":111374,"txn_amt":155.29,"txn_type":4}
{"currency":"USD","datetime":"2022-09-07T03:42:16.000Z","id":22500,"payee_acc_id":24933,"payer_acc_id":111376,"txn_amt":298.1,"txn_type":4}
{"currency":"USD","datetime":"2022-12-27T09:23:02.000Z","id":22501,"payee_acc_id":3670,"payer_acc_id":111379,"txn_amt":208.07,"txn_type":5}
{"currency":"USD","datetime":"2022-01-31T08:47:28.000Z","id":22505,"payee_acc_id":2949,"payer_acc_id":111386,"txn_amt":180.01,"txn_type":4}
{"currency":"USD","datetime":"2022-02-24T12:44:45.000Z","id":22509,"payee_acc_id":7472,"payer_acc_id":111392,"txn_amt":192.54,"txn_type":1}
{"currency":"USD","datetime":"2022-09-10T03:32:33.000Z","id":2252,"payee_acc_id":112810,"payer_acc_id":79536,"txn_amt":222.91,"txn_type":1}
{"currency":"USD","datetime":"2022-11-18T21:10:06.000Z","id":22520,"payee_acc_id":23479,"payer_acc_id":111404,"txn_amt":217.6,"txn_type":1}
{"currency":"USD","datetime":"2022-06-06T04:38:55.000Z","id":22524,"payee_acc_id":3611,"payer_acc_id":111411,"txn_amt":214.55,"txn_type":2}
{"currency":"USD","datetime":"2022-08-27T03:45:27.000Z","id":22527,"payee_acc_id":1436,"payer_acc_id":111415,"txn_amt":218.74,"txn_type":3}
{"currency":"USD","datetime":"2022-06-28T12:20:00.000Z","id":22529,"payee_acc_id":1299,"payer_acc_id":111421,"txn_amt":246.04,"txn_type":3}
{"currency":"USD","datetime":"2022-08-11T16:57:13.000Z","id":22532,"payee_acc_id":83001,"payer_acc_id":111434,"txn_amt":245.7,"txn_type":4}
{"currency":"USD","datetime":"2022-05-25T15:29:10.000Z","id":22533,"payee_acc_id":80991,"payer_acc_id":111437,"txn_amt":228.7,"txn_type":1}
{"currency":"USD","datetime":"2022-07-11T02:51:00.000Z","id":22538,"payee_acc_id":6477,"payer_acc_id":111445,"txn_amt":111.34,"txn_type":5}
{"currency":"USD","datetime":"2022-02-01T22:40:12.000Z","id":22542,"payee_acc_id":4961,"payer_acc_id":111453,"txn_amt":284.11,"txn_type":5}
{"currency":"USD","datetime":"2022-03-16T02:47:23.000Z","id":22544,"payee_acc_id":4640,"payer_acc_id":111455,"txn_amt":221.14,"txn_type":1}
{"currency":"USD","datetime":"2022-08-24T22:30:05.000Z","id":22554,"payee_acc_id":6317,"payer_acc_id":111472,"txn_amt":206.14,"txn_type":3}
{"currency":"USD","datetime":"2022-06-16T00:54:33.000Z","id":22559,"payee_acc_id":3123,"payer_acc_id":111484,"txn_amt":241.68,"txn_type":5}
{"currency":"USD","datetime":"2022-01-18T01:14:00.000Z","id":22561,"payee_acc_id":9837,"payer_acc_id":111486,"txn_amt":272.85,"txn_type":5}
{"currency":"USD","datetime":"2022-09-12T10:44:04.000Z","id":22566,"payee_acc_id":1772,"payer_acc_id":111493,"txn_amt":268.69,"txn_type":5}
{"currency":"USD","datetime":"2022-02-13T02:53:29.000Z","id":22569,"payee_acc_id":30677,"payer_acc_id":111497,"txn_amt":90.13,"txn_type":1}
{"currency":"USD","datetime":"2022-05-07T07:24:26.000Z","id":22570,"payee_acc_id":2263,"payer_acc_id":111499,"txn_amt":222.44,"txn_type":1}
{"currency":"USD","datetime":"2022-05-11T01:52:16.000Z","id":22587,"payee_acc_id":1709,"payer_acc_id":111522,"txn_amt":225.34,"txn_type":1}
{"currency":"USD","datetime":"2022-02-24T19:30:52.000Z","id":22588,"payee_acc_id":8057,"payer_acc_id":111526,"txn_amt":267.73,"txn_type":5}
{"currency":"USD","datetime":"2022-04-11T04:20:33.000Z","id":22591,"payee_acc_id":3852,"payer_acc_id":111532,"txn_amt":234.64,"txn_type":3}
{"currency":"USD","datetime":"2022-09-28T22:48:44.000Z","id":22592,"payee_acc_id":2327,"payer_acc_id":111534,"txn_amt":209.15,"txn_type":4}
{"currency":"USD","datetime":"2022-03-23T14:03:14.000Z","id":22598,"payee_acc_id":1872,"payer_acc_id":111546,"txn_amt":185.27,"txn_type":4}
{"currency":"USD","datetime":"2022-01-29T05:42:30.000Z","id":22602,"payee_acc_id":6114,"payer_acc_id":111552,"txn_amt":266.09,"txn_type":1}
{"currency":"USD","datetime":"2022-11-09T22:45:56.000Z","id":22604,"payee_acc_id":8406,"payer_acc_id":111555,"txn_amt":173.95,"txn_type":1}
{"currency":"USD","datetime":"2022-09-22T06:10:58.000Z","id":22605,"payee_acc_id":1623,"payer_acc_id":111558,"txn_amt":124.93,"txn_type":5}
{"currency":"USD","datetime":"2022-11-08T12:12:32.000Z","id":22607,"payee_acc_id":6891,"payer_acc_id":111561,"txn_amt":277.72,"txn_type":3}
{"currency":"USD","datetime":"2022-12-30T18:18:06.000Z","id":22611,"payee_acc_id":7546,"payer_acc_id":111566,"txn_amt":211.87,"txn_type":4}
{"currency":"USD","datetime":"2022-05-23T19:25:11.000Z","id":22612,"payee_acc_id":1588,"payer_acc_id":111567,"txn_amt":129.28,"txn_type":4}
{"currency":"USD","datetime":"2022-09-28T09:17:38.000Z","id":22617,"payee_acc_id":7256,"payer_acc_id":111578,"txn_amt":194.14,"txn_type":5}
{"currency":"USD","datetime":"2022-05-07T16:40:21.000Z","id":22619,"payee_acc_id":5931,"payer_acc_id":111582,"txn_amt":210.45,"txn_type":3}
{"currency":"USD","datetime":"2022-07-16T09:33:52.000Z","id":22620,"payee_acc_id":3423,"payer_acc_id":111583,"txn_amt":119.73,"txn_type":5}
{"currency":"USD","datetime":"2022-01-24T22:56:41.000Z","id":22626,"payee_acc_id":3740,"payer_acc_id":111593,"txn_amt":252.62,"txn_type":5}
{"currency":"USD","datetime":"2022-07-15T07:54:56.000Z","id":22629,"payee_acc_id":2395,"payer_acc_id":111596,"txn_amt":235.87,"txn_type":5}
{"currency":"USD","datetime":"2022-05-18T12:34:26.000Z","id":22630,"payee_acc_id":6595,"payer_acc_id":111599,"txn_amt":269.22,"txn_type":1}
{"currency":"USD","datetime":"2022-01-25T20:05:12.000Z","id":22640,"payee_acc_id":2667,"payer_acc_id":111620,"txn_amt":205.45,"txn_type":3}
{"currency":"USD","datetime":"2022-10-25T09:48:15.000Z","id":22645,"payee_acc_id":1458,"payer_acc_id":111626,"txn_amt":213.17,"txn_type":1}
{"currency":"USD","datetime":"2022-08-25T18:27:45.000Z","id":22652,"payee_acc_id":1776,"payer_acc_id":111648,"txn_amt":153.67,"txn_type":1}
{"currency":"USD","datetime":"2022-08-18T18:01:54.000Z","id":22655,"payee_acc_id":15504,"payer_acc_id":111653,"txn_amt":145.7,"txn_type":4}
{"currency":"USD","datetime":"2022-03-21T10:35:30.000Z","id":22657,"payee_acc_id":2423,"payer_acc_id":111656,"txn_amt":134.57,"txn_type":3}
{"currency":"USD","datetime":"2022-10-09T20:34:15.000Z","id":22660,"payee_acc_id":3777,"payer_acc_id":111660,"txn_amt":203.51,"txn_type":5}
{"currency":"USD","datetime":"2022-05-09T10:56:13.000Z","id":22664,"payee_acc_id":4429,"payer_acc_id":111666,"txn_amt":220.85,"txn_type":1}
{"currency":"USD","datetime":"2022-12-14T14:07:40.000Z","id":22665,"payee_acc_id":1022,"payer_acc_id":111672,"txn_amt":166.12,"txn_type":3}
{"currency":"USD","datetime":"2022-04-30T18:06:22.000Z","id":22666,"payee_acc_id":8898,"payer_acc_id":111673,"txn_amt":209.21,"txn_type":5}
{"currency":"USD","datetime":"2022-03-18T03:09:05.000Z","id":22670,"payee_acc_id":142901,"payer_acc_id":111678,"txn_amt":90.5,"txn_type":1}
{"currency":"USD","datetime":"2022-11-29T17:03:44.000Z","id":22674,"payee_acc_id":2693,"payer_acc_id":111682,"txn_amt":163.04,"txn_type":1}
{"currency":"USD","datetime":"2022-01-14T20:29:39.000Z","id":22681,"payee_acc_id":6201,"payer_acc_id":111694,"txn_amt":241.67,"txn_type":4}
{"currency":"USD","datetime":"2022-06-03T19:21:44.000Z","id":22682,"payee_acc_id":2304,"payer_acc_id":111696,"txn_amt":241.99,"txn_type":2}
{"currency":"USD","datetime":"2022-05-01T14:09:11.000Z","id":22684,"payee_acc_id":2864,"payer_acc_id":111699,"txn_amt":122.57,"txn_type":1}
{"currency":"USD","datetime":"2022-11-13T16:11:43.000Z","id":22685,"payee_acc_id":2219,"payer_acc_id":111700,"txn_amt":162.22,"txn_type":1}
{"currency":"USD","datetime":"2022-01-28T13:32:54.000Z","id":22687,"payee_acc_id":1933,"payer_acc_id":111704,"txn_amt":348.83,"txn_type":4}
{"currency":"USD","datetime":"2022-09-19T03:46:53.000Z","id":22689,"payee_acc_id":9990,"payer_acc_id":111707,"txn_amt":157.13,"txn_type":2}
{"currency":"USD","datetime":"2022-12-05T00:18:24.000Z","id":22691,"payee_acc_id":1984,"payer_acc_id":111709,"txn_amt":172.25,"txn_type":3}
{"currency":"USD","datetime":"2022-07-31T14:11:35.000Z","id":22694,"payee_acc_id":5574,"payer_acc_id":111713,"txn_amt":214.99,"txn_type":2}
{"currency":"USD","datetime":"2022-08-06T15:01:10.000Z","id":22695,"payee_acc_id":4244,"payer_acc_id":111714,"txn_amt":175.96,"txn_type":2}
{"currency":"USD","datetime":"2022-10-14T15:34:51.000Z","id":22703,"payee_acc_id":60025,"payer_acc_id":111729,"txn_amt":148.3,"txn_type":2}
{"currency":"USD","datetime":"2022-10-27T12:05:38.000Z","id":22704,"payee_acc_id":1813,"payer_acc_id":111730,"txn_amt":219.13,"txn_type":5}
{"currency":"USD","datetime":"2022-10-31T03:01:03.000Z","id":22709,"payee_acc_id":8909,"payer_acc_id":111744,"txn_amt":178.74,"txn_type":2}
{"currency":"USD","datetime":"2022-04-17T13:42:52.000Z","id":22712,"payee_acc_id":4797,"payer_acc_id":111748,"txn_amt":289.95,"txn_type":3}
{"currency":"USD","datetime":"2022-10-08T14:16:12.000Z","id":22713,"payee_acc_id":7900,"payer_acc_id":111750,"txn_amt":200.55,"txn_type":3}
{"currency":"USD","datetime":"2022-05-12T11:16:09.000Z","id":22715,"payee_acc_id":1687,"payer_acc_id":111759,"txn_amt":242.64,"txn_type":4}
{"currency":"USD","datetime":"2022-09-07T04:44:02.000Z","id":22723,"payee_acc_id":9781,"payer_acc_id":111771,"txn_amt":154.76,"txn_type":3}
{"currency":"USD","datetime":"2022-09-30T04:52:19.000Z","id":22733,"payee_acc_id":4104,"payer_acc_id":111787,"txn_amt":105.26,"txn_type":5}
{"currency":"USD","datetime":"2022-03-04T01:26:41.000Z","id":22737,"payee_acc_id":45435,"payer_acc_id":111797,"txn_amt":261.3,"txn_type":4}
{"currency":"USD","datetime":"2022-05-19T05:37:22.000Z","id":22738,"payee_acc_id":1588,"payer_acc_id":111800,"txn_amt":220.82,"txn_type":5}
{"currency":"USD","datetime":"2022-01-21T14:34:20.000Z","id":22741,"payee_acc_id":2269,"payer_acc_id":111807,"txn_amt":177.64,"txn_type":1}
{"currency":"USD","datetime":"2022-08-22T12:10:24.000Z","id":22742,"payee_acc_id":1029,"payer_acc_id":111809,"txn_amt":155.88,"txn_type":3}
{"currency":"USD","datetime":"2022-02-15T02:00:06.000Z","id":22746,"payee_acc_id":6338,"payer_acc_id":111815,"txn_amt":172.85,"txn_type":5}
{"currency":"USD","datetime":"2022-12-12T17:15:58.000Z","id":22750,"payee_acc_id":88447,"payer_acc_id":111823,"txn_amt":99.52,"txn_type":4}
{"currency":"USD","datetime":"2022-09-05T06:10:03.000Z","id":22755,"payee_acc_id":1588,"payer_acc_id":111831,"txn_amt":225.37,"txn_type":4}
{"currency":"USD","datetime":"2022-07-16T00:03:51.000Z","id":22757,"payee_acc_id":7731,"payer_acc_id":111833,"txn_amt":269.17,"txn_type":4}
{"currency":"USD","datetime":"2022-11-18T02:04:55.000Z","id":22763,"payee_acc_id":9003,"payer_acc_id":111839,"txn_amt":203.64,"txn_type":5}
{"currency":"USD","datetime":"2022-12-10T12:10:10.000Z","id":22764,"payee_acc_id":7800,"payer_acc_id":111841,"txn_amt":201.41,"txn_type":2}
{"currency":"USD","datetime":"2022-05-10T11:44:29.000Z","id":22766,"payee_acc_id":11395,"payer_acc_id":111844,"txn_amt":240.4,"txn_type":1}
{"currency":"USD","datetime":"2022-10-04T07:41:38.000Z","id":22774,"payee_acc_id":4031,"payer_acc_id":111872,"txn_amt":215.52,"txn_type":5}
{"currency":"USD","datetime":"2022-12-15T13:50:14.000Z","id":22777,"payee_acc_id":5095,"payer_acc_id":111877,"txn_amt":187.71,"txn_type":2}
{"currency":"USD","datetime":"2022-09-26T08:24:22.000Z","id":22783,"payee_acc_id":8254,"payer_acc_id":111885,"txn_amt":304.19,"txn_type":3}
{"currency":"USD","datetime":"2022-10-26T09:11:00.000Z","id":22785,"payee_acc_id":8670,"payer_acc_id":111888,"txn_amt":240.11,"txn_type":2}
{"currency":"USD","datetime":"2022-06-21T07:18:45.000Z","id":22791,"payee_acc_id":1373,"payer_acc_id":111899,"txn_amt":191.88,"txn_type":4}
{"currency":"USD","datetime":"2022-10-29T18:25:42.000Z","id":22794,"payee_acc_id":31733,"payer_acc_id":111905,"txn_amt":203.3,"txn_type":3}
{"currency":"USD","datetime":"2022-02-13T22:27:29.000Z","id":22796,"payee_acc_id":4147,"payer_acc_id":111908,"txn_amt":268.67,"txn_type":3}
{"currency":"USD","datetime":"2022-11-09T00:08:34.000Z","id":22801,"payee_acc_id":7556,"payer_acc_id":111923,"txn_amt":171.21,"txn_type":2}
{"currency":"USD","datetime":"2022-11-16T14:12:48.000Z","id":22807,"payee_acc_id":1278,"payer_acc_id":111932,"txn_amt":200.78,"txn_type":2}
{"currency":"USD","datetime":"2022-03-13T05:48:00.000Z","id":22808,"payee_acc_id":4984,"payer_acc_id":111935,"txn_amt":149.19,"txn_type":4}
{"currency":"USD","datetime":"2022-09-10T17:20:09.000Z","id":22820,"payee_acc_id":3641,"payer_acc_id":111956,"txn_amt":257.93,"txn_type":2}
{"currency":"USD","datetime":"2022-01-11T02:06:45.000Z","id":22822,"payee_acc_id":3164,"payer_acc_id":111961,"txn_amt":163.44,"txn_type":4}
{"currency":"USD","datetime":"2022-09-18T06:13:03.000Z","id":22824,"payee_acc_id":1832,"payer_acc_id":111962,"txn_amt":209.75,"txn_type":1}
{"currency":"USD","datetime":"2022-10-18T05:51:22.000Z","id":22834,"payee_acc_id":1045,"payer_acc_id":111974,"txn_amt":260.66,"txn_type":2}
{"currency":"USD","datetime":"2022-02-13T06:47:45.000Z","id":2284,"payee_acc_id":145128,"payer_acc_id":79582,"txn_amt":239.88,"txn_type":5}
{"currency":"USD","datetime":"2022-02-10T17:36:28.000Z","id":22846,"payee_acc_id":6407,"payer_acc_id":111999,"txn_amt":226.15,"txn_type":5}
{"currency":"USD","datetime":"2022-05-21T04:24:44.000Z","id":22850,"payee_acc_id":5669,"payer_acc_id":112008,"txn_amt":272.85,"txn_type":3}
{"currency":"USD","datetime":"2022-06-09T22:08:06.000Z","id":22855,"payee_acc_id":1380,"payer_acc_id":112014,"txn_amt":309.57,"txn_type":1}
{"currency":"USD","datetime":"2022-03-02T01:09:31.000Z","id":22863,"payee_acc_id":1236,"payer_acc_id":112026,"txn_amt":220.11,"txn_type":5}
{"currency":"USD","datetime":"2022-10-06T06:39:57.000Z","id":22867,"payee_acc_id":2275,"payer_acc_id":112033,"txn_amt":240.92,"txn_type":2}
{"currency":"USD","datetime":"2022-09-24T19:16:36.000Z","id":22872,"payee_acc_id":2779,"payer_acc_id":112042,"txn_amt":247.09,"txn_type":5}
{"currency":"USD","datetime":"2022-09-03T18:13:38.000Z","id":22873,"payee_acc_id":1150,"payer_acc_id":112043,"txn_amt":169.78,"txn_type":4}
{"currency":"USD","datetime":"2022-07-30T21:47:16.000Z","id":22875,"payee_acc_id":7295,"payer_acc_id":112045,"txn_amt":194.61,"txn_type":5}
{"currency":"USD","datetime":"2022-01-06T10:14:39.000Z","id":22879,"payee_acc_id":4858,"payer_acc_id":112048,"txn_amt":205.31,"txn_type":3}
{"currency":"USD","datetime":"2022-01-17T10:25:08.000Z","id":22881,"payee_acc_id":64113,"payer_acc_id":112055,"txn_amt":166.2,"txn_type":3}
{"currency":"USD","datetime":"2022-04-17T18:21:16.000Z","id":22887,"payee_acc_id":1509,"payer_acc_id":112067,"txn_amt":263.75,"txn_type":4}
{"currency":"USD","datetime":"2022-09-27T23:02:27.000Z","id":22899,"payee_acc_id":7588,"payer_acc_id":112089,"txn_amt":228.58,"txn_type":4}
{"currency":"USD","datetime":"2022-03-06T01:19:49.000Z","id":22900,"payee_acc_id":73662,"payer_acc_id":112090,"txn_amt":105.8,"txn_type":1}
{"currency":"USD","datetime":"2022-05-16T18:59:07.000Z","id":22901,"payee_acc_id":2349,"payer_acc_id":112090,"txn_amt":252.05,"txn_type":3}
{"currency":"USD","datetime":"2022-01-02T00:42:28.000Z","id":22905,"payee_acc_id":7256,"payer_acc_id":112102,"txn_amt":218.75,"txn_type":1}
{"currency":"USD","datetime":"2022-11-09T04:04:49.000Z","id":22908,"payee_acc_id":53431,"payer_acc_id":112106,"txn_amt":228.1,"txn_type":5}
{"currency":"USD","datetime":"2022-01-17T11:50:19.000Z","id":2291,"payee_acc_id":106181,"payer_acc_id":79587,"txn_amt":158.85,"txn_type":5}
{"currency":"USD","datetime":"2022-09-03T04:53:22.000Z","id":22911,"payee_acc_id":3787,"payer_acc_id":112110,"txn_amt":239.65,"txn_type":2}
{"currency":"USD","datetime":"2022-07-19T04:41:04.000Z","id":22924,"payee_acc_id":3300,"payer_acc_id":112135,"txn_amt":184.65,"txn_type":1}
{"currency":"USD","datetime":"2022-03-11T06:29:55.000Z","id":22927,"payee_acc_id":9321,"payer_acc_id":112139,"txn_amt":332.61,"txn_type":2}
{"currency":"USD","datetime":"2022-05-12T01:25:45.000Z","id":22928,"payee_acc_id":14202,"payer_acc_id":112140,"txn_amt":217.7,"txn_type":4}
{"currency":"USD","datetime":"2022-08-13T01:56:38.000Z","id":22931,"payee_acc_id":1668,"payer_acc_id":112146,"txn_amt":247.03,"txn_type":2}
{"currency":"USD","datetime":"2022-10-15T15:17:08.000Z","id":22935,"payee_acc_id":1099,"payer_acc_id":112151,"txn_amt":220.87,"txn_type":3}
{"currency":"USD","datetime":"2022-11-30T19:39:35.000Z","id":22936,"payee_acc_id":2214,"payer_acc_id":112152,"txn_amt":197.36,"txn_type":3}
{"currency":"USD","datetime":"2022-04-02T22:39:11.000Z","id":22939,"payee_acc_id":7015,"payer_acc_id":112156,"txn_amt":187.04,"txn_type":3}
{"currency":"USD","datetime":"2022-06-28T01:26:26.000Z","id":22941,"payee_acc_id":1747,"payer_acc_id":112161,"txn_amt":255.93,"txn_type":2}
{"currency":"USD","datetime":"2022-10-10T09:11:37.000Z","id":22945,"payee_acc_id":3023,"payer_acc_id":112168,"txn_amt":219.57,"txn_type":1}
{"currency":"USD","datetime":"2022-04-14T14:11:53.000Z","id":22951,"payee_acc_id":1910,"payer_acc_id":112178,"txn_amt":250.17,"txn_type":5}
{"currency":"USD","datetime":"2022-12-11T21:26:17.000Z","id":22953,"payee_acc_id":6055,"payer_acc_id":112184,"txn_amt":180.97,"txn_type":2}
{"currency":"USD","datetime":"2022-05-31T20:57:02.000Z","id":22957,"payee_acc_id":3319,"payer_acc_id":112189,"txn_amt":237.82,"txn_type":1}
{"currency":"USD","datetime":"2022-09-02T01:03:48.000Z","id":22964,"payee_acc_id":3275,"payer_acc_id":112197,"txn_amt":177.87,"txn_type":3}
{"currency":"USD","datetime":"2022-07-13T00:52:51.000Z","id":22972,"payee_acc_id":59654,"payer_acc_id":112214,"txn_amt":240.8,"txn_type":2}
{"currency":"USD","datetime":"2022-08-26T02:54:23.000Z","id":22979,"payee_acc_id":5421,"payer_acc_id":112230,"txn_amt":231.43,"txn_type":5}
{"currency":"USD","datetime":"2022-10-24T06:54:35.000Z","id":22992,"payee_acc_id":1768,"payer_acc_id":112260,"txn_amt":298.67,"txn_type":4}
{"currency":"USD","datetime":"2022-01-02T10:01:18.000Z","id":22993,"payee_acc_id":9330,"payer_acc_id":112262,"txn_amt":219.06,"txn_type":1}
{"currency":"USD","datetime":"2022-06-13T06:37:42.000Z","id":22995,"payee_acc_id":21310,"payer_acc_id":112263,"txn_amt":283.4,"txn_type":4}
{"currency":"USD","datetime":"2022-11-28T09:40:21.000Z","id":22998,"payee_acc_id":85421,"payer_acc_id":112266,"txn_amt":193.8,"txn_type":2}
{"currency":"USD","datetime":"2022-06-14T06:52:18.000Z","id":22999,"payee_acc_id":16832,"payer_acc_id":112269,"txn_amt":236.2,"txn_type":4}
{"currency":"USD","datetime":"2022-11-22T10:57:03.000Z","id":23000,"payee_acc_id":3989,"payer_acc_id":112270,"txn_amt":190.73,"txn_type":1}
{"currency":"USD","datetime":"2022-08-26T01:54:37.000Z","id":23003,"payee_acc_id":1668,"payer_acc_id":112275,"txn_amt":166.74,"txn_type":2}
{"currency":"USD","datetime":"2022-10-28T03:45:17.000Z","id":23005,"payee_acc_id":1327,"payer_acc_id":112277,"txn_amt":125.25,"txn_type":3}
{"currency":"USD","datetime":"2022-07-06T23:45:22.000Z","id":23009,"payee_acc_id":4314,"payer_acc_id":112287,"txn_amt":157.57,"txn_type":5}
{"currency":"USD","datetime":"2022-04-06T00:34:02.000Z","id":23020,"payee_acc_id":1911,"payer_acc_id":112305,"txn_amt":233.16,"txn_type":3}
{"currency":"USD","datetime":"2022-12-14T06:13:25.000Z","id":23021,"payee_acc_id":4350,"payer_acc_id":112309,"txn_amt":258.19,"txn_type":5}
{"currency":"USD","datetime":"2022-02-23T09:10:42.000Z","id":23024,"payee_acc_id":5549,"payer_acc_id":112314,"txn_amt":162.27,"txn_type":2}
{"currency":"USD","datetime":"2022-09-01T20:25:10.000Z","id":23027,"payee_acc_id":1022,"payer_acc_id":112323,"txn_amt":304.18,"txn_type":3}
{"currency":"USD","datetime":"2022-10-27T07:39:29.000Z","id":23028,"payee_acc_id":29286,"payer_acc_id":112324,"txn_amt":85.45,"txn_type":1}
{"currency":"USD","datetime":"2022-07-01T17:33:51.000Z","id":23031,"payee_acc_id":7731,"payer_acc_id":112331,"txn_amt":240.92,"txn_type":3}
{"currency":"USD","datetime":"2022-01-31T13:43:10.000Z","id":23036,"payee_acc_id":6436,"payer_acc_id":112337,"txn_amt":238.74,"txn_type":2}
{"currency":"USD","datetime":"2022-08-19T22:02:04.000Z","id":23037,"payee_acc_id":6510,"payer_acc_id":112340,"txn_amt":210.57,"txn_type":3}
{"currency":"USD","datetime":"2022-05-25T02:29:05.000Z","id":23040,"payee_acc_id":2106,"payer_acc_id":112343,"txn_amt":183.34,"txn_type":5}
{"currency":"USD","datetime":"2022-12-01T04:39:31.000Z","id":23041,"payee_acc_id":5959,"payer_acc_id":112344,"txn_amt":101.96,"txn_type":5}
{"currency":"USD","datetime":"2022-03-04T16:31:51.000Z","id":23043,"payee_acc_id":1109,"payer_acc_id":112346,"txn_amt":173.53,"txn_type":5}
{"currency":"USD","datetime":"2022-04-19T17:21:27.000Z","id":23047,"payee_acc_id":1227,"payer_acc_id":112354,"txn_amt":197.24,"txn_type":1}
{"currency":"USD","datetime":"2022-10-25T12:07:33.000Z","id":23050,"payee_acc_id":1666,"payer_acc_id":112357,"txn_amt":310.86,"txn_type":4}
{"currency":"USD","datetime":"2022-03-15T18:41:10.000Z","id":23053,"payee_acc_id":2484,"payer_acc_id":112362,"txn_amt":283.58,"txn_type":1}
{"currency":"USD","datetime":"2022-08-01T01:44:59.000Z","id":23054,"payee_acc_id":1446,"payer_acc_id":112363,"txn_amt":273.04,"txn_type":2}
{"currency":"USD","datetime":"2022-07-02T15:59:20.000Z","id":23056,"payee_acc_id":2455,"payer_acc_id":112366,"txn_amt":116.04,"txn_type":2}
{"currency":"USD","datetime":"2022-07-30T00:24:42.000Z","id":23062,"payee_acc_id":8756,"payer_acc_id":112384,"txn_amt":233.96,"txn_type":2}
{"currency":"USD","datetime":"2022-07-19T18:42:46.000Z","id":23072,"payee_acc_id":65681,"payer_acc_id":112405,"txn_amt":196.8,"txn_type":5}
{"currency":"USD","datetime":"2022-07-28T06:35:49.000Z","id":23076,"payee_acc_id":5631,"payer_acc_id":112416,"txn_amt":154.99,"txn_type":2}
{"currency":"USD","datetime":"2022-02-12T01:29:27.000Z","id":23077,"payee_acc_id":5988,"payer_acc_id":112417,"txn_amt":187.63,"txn_type":1}
{"currency":"USD","datetime":"2022-05-13T06:43:41.000Z","id":23079,"payee_acc_id":4164,"payer_acc_id":112419,"txn_amt":240.87,"txn_type":4}
{"currency":"USD","datetime":"2022-11-21T18:46:27.000Z","id":2309,"payee_acc_id":117440,"payer_acc_id":79610,"txn_amt":143.29,"txn_type":2}
{"currency":"USD","datetime":"2022-03-20T09:03:02.000Z","id":23091,"payee_acc_id":1690,"payer_acc_id":112443,"txn_amt":130.43,"txn_type":4}
{"currency":"USD","datetime":"2022-05-04T06:37:18.000Z","id":23092,"payee_acc_id":1502,"payer_acc_id":112444,"txn_amt":140.07,"txn_type":3}
{"currency":"USD","datetime":"2022-01-07T21:31:47.000Z","id":23098,"payee_acc_id":4036,"payer_acc_id":112450,"txn_amt":175.93,"txn_type":1}
{"currency":"USD","datetime":"2022-03-29T09:35:18.000Z","id":23104,"payee_acc_id":5805,"payer_acc_id":112456,"txn_amt":177.86,"txn_type":3}
{"currency":"USD","datetime":"2022-08-30T21:27:08.000Z","id":23108,"payee_acc_id":1339,"payer_acc_id":112465,"txn_amt":224.52,"txn_type":5}
{"currency":"USD","datetime":"2022-11-23T21:41:35.000Z","id":23109,"payee_acc_id":24954,"payer_acc_id":112466,"txn_amt":218.6,"txn_type":1}
{"currency":"USD","datetime":"2022-06-07T22:31:42.000Z","id":23117,"payee_acc_id":2144,"payer_acc_id":112491,"txn_amt":157.02,"txn_type":2}
{"currency":"USD","datetime":"2022-12-25T13:22:17.000Z","id":23125,"payee_acc_id":3825,"payer_acc_id":112507,"txn_amt":176.51,"txn_type":2}
{"currency":"USD","datetime":"2022-09-19T19:25:35.000Z","id":23129,"payee_acc_id":8282,"payer_acc_id":112513,"txn_amt":200.01,"txn_type":2}
{"currency":"USD","datetime":"2022-12-25T11:39:56.000Z","id":23130,"payee_acc_id":42176,"payer_acc_id":112514,"txn_amt":256.5,"txn_type":1}
{"currency":"USD","datetime":"2022-11-26T23:12:56.000Z","id":23131,"payee_acc_id":4086,"payer_acc_id":112515,"txn_amt":200.87,"txn_type":2}
{"currency":"USD","datetime":"2022-07-08T23:41:17.000Z","id":23136,"payee_acc_id":3204,"payer_acc_id":112528,"txn_amt":173.44,"txn_type":1}
{"currency":"USD","datetime":"2022-03-24T01:15:55.000Z","id":23141,"payee_acc_id":74592,"payer_acc_id":112534,"txn_amt":202.7,"txn_type":2}
{"currency":"USD","datetime":"2022-10-19T13:37:07.000Z","id":23144,"payee_acc_id":1848,"payer_acc_id":112537,"txn_amt":175.05,"txn_type":2}
{"currency":"USD","datetime":"2022-08-16T18:22:47.000Z","id":23147,"payee_acc_id":5677,"payer_acc_id":112548,"txn_amt":238.45,"txn_type":4}
{"currency":"USD","datetime":"2022-05-18T11:58:43.000Z","id":23149,"payee_acc_id":2429,"payer_acc_id":112552,"txn_amt":135.34,"txn_type":2}
{"currency":"USD","datetime":"2022-02-07T23:58:48.000Z","id":23150,"payee_acc_id":7622,"payer_acc_id":112553,"txn_amt":171.53,"txn_type":2}
{"currency":"USD","datetime":"2022-11-19T11:29:35.000Z","id":23154,"payee_acc_id":2565,"payer_acc_id":112557,"txn_amt":289.54,"txn_type":2}
{"currency":"USD","datetime":"2022-04-04T11:53:12.000Z","id":23155,"payee_acc_id":6465,"payer_acc_id":112559,"txn_amt":162.19,"txn_type":1}
{"currency":"USD","datetime":"2022-11-30T07:42:42.000Z","id":23156,"payee_acc_id":8603,"payer_acc_id":112560,"txn_amt":182.54,"txn_type":2}
{"currency":"USD","datetime":"2022-12-16T18:09:20.000Z","id":23158,"payee_acc_id":4080,"payer_acc_id":112563,"txn_amt":164.85,"txn_type":4}
{"currency":"USD","datetime":"2022-10-24T00:01:31.000Z","id":23160,"payee_acc_id":1263,"payer_acc_id":112566,"txn_amt":172.79,"txn_type":4}
{"currency":"USD","datetime":"2022-03-03T04:29:46.000Z","id":23165,"payee_acc_id":4309,"payer_acc_id":112577,"txn_amt":191.65,"txn_type":4}
{"currency":"USD","datetime":"2022-12-25T16:03:34.000Z","id":23172,"payee_acc_id":2578,"payer_acc_id":112594,"txn_amt":140.07,"txn_type":4}
{"currency":"USD","datetime":"2022-10-12T23:07:03.000Z","id":23174,"payee_acc_id":1396,"payer_acc_id":112601,"txn_amt":198.06,"txn_type":5}
{"currency":"USD","datetime":"2022-11-18T11:53:04.000Z","id":23177,"payee_acc_id":9287,"payer_acc_id":112606,"txn_amt":210.84,"txn_type":2}
{"currency":"USD","datetime":"2022-12-03T12:47:57.000Z","id":23179,"payee_acc_id":2497,"payer_acc_id":112608,"txn_amt":191.41,"txn_type":2}
{"currency":"USD","datetime":"2022-07-15T11:50:01.000Z","id":23183,"payee_acc_id":46340,"payer_acc_id":112614,"txn_amt":97.28,"txn_type":1}
{"currency":"USD","datetime":"2022-05-13T18:38:45.000Z","id":23193,"payee_acc_id":2237,"payer_acc_id":112631,"txn_amt":186.44,"txn_type":2}
{"currency":"USD","datetime":"2022-11-30T21:07:37.000Z","id":23202,"payee_acc_id":1411,"payer_acc_id":112647,"txn_amt":180.08,"txn_type":4}
{"currency":"USD","datetime":"2022-01-03T11:49:28.000Z","id":23203,"payee_acc_id":7677,"payer_acc_id":112648,"txn_amt":169.32,"txn_type":4}
{"currency":"USD","datetime":"2022-09-28T11:17:08.000Z","id":23208,"payee_acc_id":5565,"payer_acc_id":112656,"txn_amt":154.11,"txn_type":5}
{"currency":"USD","datetime":"2022-02-18T00:42:28.000Z","id":23209,"payee_acc_id":3386,"payer_acc_id":112661,"txn_amt":258.47,"txn_type":1}
{"currency":"USD","datetime":"2022-07-27T07:48:34.000Z","id":23212,"payee_acc_id":10005,"payer_acc_id":112665,"txn_amt":247.7,"txn_type":3}
{"currency":"USD","datetime":"2022-12-16T02:44:23.000Z","id":23229,"payee_acc_id":6883,"payer_acc_id":112694,"txn_amt":235.64,"txn_type":5}
{"currency":"USD","datetime":"2022-03-18T19:01:45.000Z","id":23235,"payee_acc_id":1824,"payer_acc_id":112705,"txn_amt":237.16,"txn_type":5}
{"currency":"USD","datetime":"2022-11-24T20:14:50.000Z","id":23242,"payee_acc_id":3862,"payer_acc_id":112714,"txn_amt":212.08,"txn_type":5}
{"currency":"USD","datetime":"2022-12-08T02:29:12.000Z","id":23247,"payee_acc_id":2103,"payer_acc_id":112721,"txn_amt":272.28,"txn_type":1}
{"currency":"USD","datetime":"2022-02-01T10:46:37.000Z","id":23250,"payee_acc_id":77470,"payer_acc_id":112724,"txn_amt":223.1,"txn_type":5}
{"currency":"USD","datetime":"2022-12-28T01:53:10.000Z","id":23254,"payee_acc_id":1181,"payer_acc_id":112729,"txn_amt":224.26,"txn_type":3}
{"currency":"USD","datetime":"2022-09-25T13:31:53.000Z","id":23255,"payee_acc_id":8223,"payer_acc_id":112730,"txn_amt":225.26,"txn_type":3}
{"currency":"USD","datetime":"2022-02-07T04:15:00.000Z","id":23265,"payee_acc_id":5122,"payer_acc_id":112754,"txn_amt":131.56,"txn_type":3}
{"currency":"USD","datetime":"2022-05-26T02:57:49.000Z","id":23271,"payee_acc_id":1262,"payer_acc_id":112771,"txn_amt":222.07,"txn_type":2}
{"currency":"USD","datetime":"2022-02-17T17:28:35.000Z","id":23274,"payee_acc_id":1022,"payer_acc_id":112776,"txn_amt":159.59,"txn_type":1}
{"currency":"USD","datetime":"2022-11-18T13:36:03.000Z","id":23285,"payee_acc_id":2849,"payer_acc_id":112800,"txn_amt":196.35,"txn_type":3}
{"currency":"USD","datetime":"2022-04-05T08:34:09.000Z","id":23291,"payee_acc_id":1389,"payer_acc_id":112815,"txn_amt":213.39,"txn_type":4}
{"currency":"USD","datetime":"2022-05-04T13:57:01.000Z","id":23292,"payee_acc_id":1090,"payer_acc_id":112819,"txn_amt":158.84,"txn_type":4}
{"currency":"USD","datetime":"2022-04-16T09:49:53.000Z","id":23295,"payee_acc_id":1828,"payer_acc_id":112827,"txn_amt":214.75,"txn_type":5}
{"currency":"USD","datetime":"2022-01-04T18:57:38.000Z","id":23296,"payee_acc_id":5621,"payer_acc_id":112828,"txn_amt":200.92,"txn_type":2}
{"currency":"USD","datetime":"2022-12-16T00:28:15.000Z","id":23301,"payee_acc_id":3196,"payer_acc_id":112845,"txn_amt":125.49,"txn_type":3}
{"currency":"USD","datetime":"2022-08-10T10:24:12.000Z","id":23306,"payee_acc_id":4202,"payer_acc_id":112858,"txn_amt":237.72,"txn_type":3}
{"currency":"USD","datetime":"2022-10-05T13:05:49.000Z","id":23308,"payee_acc_id":6273,"payer_acc_id":112862,"txn_amt":147.21,"txn_type":4}
{"currency":"USD","datetime":"2022-12-22T12:26:34.000Z","id":23310,"payee_acc_id":58149,"payer_acc_id":112867,"txn_amt":283.2,"txn_type":2}
{"currency":"USD","datetime":"2022-04-09T09:23:27.000Z","id":23311,"payee_acc_id":2332,"payer_acc_id":112868,"txn_amt":134.14,"txn_type":1}
{"currency":"USD","datetime":"2022-07-09T02:46:14.000Z","id":23313,"payee_acc_id":24043,"payer_acc_id":112870,"txn_amt":243.7,"txn_type":3}
{"currency":"USD","datetime":"2022-02-04T23:19:12.000Z","id":23322,"payee_acc_id":1401,"payer_acc_id":112887,"txn_amt":168.41,"txn_type":2}
{"currency":"USD","datetime":"2022-11-06T21:13:17.000Z","id":23329,"payee_acc_id":9735,"payer_acc_id":112896,"txn_amt":207.74,"txn_type":2}
{"currency":"USD","datetime":"2022-04-03T11:02:34.000Z","id":23331,"payee_acc_id":1247,"payer_acc_id":112897,"txn_amt":173.78,"txn_type":5}
{"currency":"USD","datetime":"2022-08-26T01:09:39.000Z","id":23333,"payee_acc_id":1423,"payer_acc_id":112901,"txn_amt":204.73,"txn_type":3}
{"currency":"USD","datetime":"2022-01-31T21:54:11.000Z","id":23334,"payee_acc_id":16860,"payer_acc_id":112902,"txn_amt":206.2,"txn_type":3}
{"currency":"USD","datetime":"2022-11-06T10:57:25.000Z","id":23341,"payee_acc_id":7297,"payer_acc_id":112913,"txn_amt":142.56,"txn_type":5}
{"currency":"USD","datetime":"2022-01-08T15:30:09.000Z","id":23347,"payee_acc_id":36202,"payer_acc_id":112928,"txn_amt":222.7,"txn_type":1}
{"currency":"USD","datetime":"2022-06-12T10:22:02.000Z","id":23349,"payee_acc_id":6072,"payer_acc_id":112930,"txn_amt":158.36,"txn_type":4}
{"currency":"USD","datetime":"2022-04-28T03:09:30.000Z","id":23359,"payee_acc_id":23335,"payer_acc_id":112952,"txn_amt":190.3,"txn_type":3}
{"currency":"USD","datetime":"2022-11-25T13:00:47.000Z","id":23368,"payee_acc_id":3036,"payer_acc_id":112967,"txn_amt":240.69,"txn_type":4}
{"currency":"USD","datetime":"2022-10-15T07:27:34.000Z","id":23376,"payee_acc_id":1099,"payer_acc_id":112982,"txn_amt":154.12,"txn_type":1}
{"currency":"USD","datetime":"2022-01-18T12:44:13.000Z","id":23379,"payee_acc_id":4592,"payer_acc_id":112987,"txn_amt":211.32,"txn_type":5}
{"currency":"USD","datetime":"2022-10-16T01:23:02.000Z","id":23384,"payee_acc_id":5796,"payer_acc_id":112998,"txn_amt":219.99,"txn_type":5}
{"currency":"USD","datetime":"2022-05-14T13:26:29.000Z","id":23385,"payee_acc_id":2497,"payer_acc_id":113002,"txn_amt":155.46,"txn_type":3}
{"currency":"USD","datetime":"2022-12-02T06:55:33.000Z","id":23388,"payee_acc_id":56165,"payer_acc_id":113007,"txn_amt":108.7,"txn_type":5}
{"currency":"USD","datetime":"2022-06-10T07:57:30.000Z","id":23392,"payee_acc_id":1830,"payer_acc_id":113015,"txn_amt":206.17,"txn_type":1}
{"currency":"USD","datetime":"2022-09-20T21:08:52.000Z","id":23395,"payee_acc_id":3955,"payer_acc_id":113018,"txn_amt":287.02,"txn_type":2}
{"currency":"USD","datetime":"2022-04-11T01:39:59.000Z","id":23402,"payee_acc_id":15907,"payer_acc_id":113030,"txn_amt":270.2,"txn_type":1}
{"currency":"USD","datetime":"2022-12-27T17:34:32.000Z","id":23411,"payee_acc_id":2863,"payer_acc_id":113050,"txn_amt":271.12,"txn_type":5}
{"currency":"USD","datetime":"2022-05-27T01:08:19.000Z","id":23412,"payee_acc_id":1191,"payer_acc_id":113051,"txn_amt":162.83,"txn_type":5}
{"currency":"USD","datetime":"2022-09-29T21:42:08.000Z","id":23414,"payee_acc_id":3084,"payer_acc_id":113057,"txn_amt":125.12,"txn_type":1}
{"currency":"USD","datetime":"2022-10-06T13:44:51.000Z","id":23416,"payee_acc_id":3138,"payer_acc_id":113060,"txn_amt":234.39,"txn_type":1}
{"currency":"USD","datetime":"2022-07-05T08:09:50.000Z","id":23419,"payee_acc_id":1397,"payer_acc_id":113063,"txn_amt":149.67,"txn_type":3}
{"currency":"USD","datetime":"2022-12-30T23:11:30.000Z","id":23424,"payee_acc_id":6015,"payer_acc_id":113074,"txn_amt":250.63,"txn_type":3}
{"currency":"USD","datetime":"2022-09-11T06:29:01.000Z","id":23435,"payee_acc_id":9819,"payer_acc_id":113087,"txn_amt":260.93,"txn_type":3}
{"currency":"USD","datetime":"2022-05-04T13:29:12.000Z","id":23447,"payee_acc_id":32694,"payer_acc_id":113101,"txn_amt":188.7,"txn_type":4}
{"currency":"USD","datetime":"2022-06-27T05:53:47.000Z","id":23449,"payee_acc_id":4126,"payer_acc_id":113104,"txn_amt":177.98,"txn_type":2}
{"currency":"USD","datetime":"2022-11-04T02:27:14.000Z","id":23456,"payee_acc_id":5886,"payer_acc_id":113123,"txn_amt":243.73,"txn_type":2}
{"currency":"USD","datetime":"2022-02-01T10:03:28.000Z","id":23463,"payee_acc_id":9082,"payer_acc_id":113134,"txn_amt":232.91,"txn_type":5}
{"currency":"USD","datetime":"2022-04-24T14:09:30.000Z","id":23465,"payee_acc_id":4584,"payer_acc_id":113141,"txn_amt":217.05,"txn_type":2}
{"currency":"USD","datetime":"2022-12-18T08:22:07.000Z","id":23469,"payee_acc_id":1767,"payer_acc_id":113144,"txn_amt":257.91,"txn_type":4}
{"currency":"USD","datetime":"2022-01-07T12:39:45.000Z","id":23474,"payee_acc_id":1437,"payer_acc_id":113153,"txn_amt":200.11,"txn_type":4}
{"currency":"USD","datetime":"2022-08-05T08:10:14.000Z","id":23476,"payee_acc_id":1709,"payer_acc_id":113157,"txn_amt":233.31,"txn_type":2}
{"currency":"USD","datetime":"2022-03-27T14:51:12.000Z","id":23480,"payee_acc_id":9610,"payer_acc_id":113164,"txn_amt":181.91,"txn_type":4}
{"currency":"USD","datetime":"2022-10-19T14:31:06.000Z","id":23484,"payee_acc_id":5718,"payer_acc_id":113168,"txn_amt":215.99,"txn_type":5}
{"currency":"USD","datetime":"2022-04-14T00:34:49.000Z","id":23485,"payee_acc_id":10324,"payer_acc_id":113169,"txn_amt":157.7,"txn_type":3}
{"currency":"USD","datetime":"2022-04-11T20:41:27.000Z","id":23486,"payee_acc_id":33231,"payer_acc_id":113172,"txn_amt":187.5,"txn_type":4}
{"currency":"USD","datetime":"2022-02-23T21:52:07.000Z","id":23490,"payee_acc_id":1275,"payer_acc_id":113179,"txn_amt":186.99,"txn_type":5}
{"currency":"USD","datetime":"2022-06-29T18:35:10.000Z","id":23497,"payee_acc_id":3273,"payer_acc_id":113192,"txn_amt":208.36,"txn_type":3}
{"currency":"USD","datetime":"2022-05-31T00:10:12.000Z","id":23503,"payee_acc_id":1826,"payer_acc_id":113198,"txn_amt":209.71,"txn_type":2}
{"currency":"USD","datetime":"2022-09-13T10:01:02.000Z","id":23505,"payee_acc_id":16091,"payer_acc_id":113202,"txn_amt":222.5,"txn_type":3}
{"currency":"USD","datetime":"2022-11-03T04:52:44.000Z","id":23509,"payee_acc_id":12165,"payer_acc_id":113207,"txn_amt":219.0,"txn_type":2}
{"currency":"USD","datetime":"2022-07-12T06:04:00.000Z","id":23510,"payee_acc_id":6141,"payer_acc_id":113208,"txn_amt":239.06,"txn_type":2}
{"currency":"USD","datetime":"2022-06-19T09:59:58.000Z","id":23511,"payee_acc_id":83801,"payer_acc_id":113211,"txn_amt":154.8,"txn_type":2}
{"currency":"USD","datetime":"2022-05-14T21:14:16.000Z","id":23517,"payee_acc_id":2262,"payer_acc_id":113223,"txn_amt":271.61,"txn_type":3}
{"currency":"USD","datetime":"2022-01-07T20:59:22.000Z","id":23522,"payee_acc_id":1850,"payer_acc_id":113236,"txn_amt":200.63,"txn_type":4}
{"currency":"USD","datetime":"2022-10-09T02:32:05.000Z","id":23529,"payee_acc_id":1575,"payer_acc_id":113251,"txn_amt":236.51,"txn_type":2}
{"currency":"USD","datetime":"2022-03-01T18:23:22.000Z","id":23547,"payee_acc_id":6294,"payer_acc_id":113284,"txn_amt":234.91,"txn_type":4}
{"currency":"USD","datetime":"2022-10-22T01:48:52.000Z","id":23555,"payee_acc_id":52600,"payer_acc_id":113293,"txn_amt":232.1,"txn_type":5}
{"currency":"USD","datetime":"2022-01-26T16:35:16.000Z","id":23560,"payee_acc_id":1767,"payer_acc_id":113298,"txn_amt":182.55,"txn_type":4}
{"currency":"USD","datetime":"2022-05-23T02:14:31.000Z","id":23565,"payee_acc_id":6177,"payer_acc_id":113306,"txn_amt":172.18,"txn_type":1}
{"currency":"USD","datetime":"2022-07-21T07:48:37.000Z","id":23577,"payee_acc_id":3110,"payer_acc_id":113329,"txn_amt":238.89,"txn_type":5}
{"currency":"USD","datetime":"2022-11-26T13:03:40.000Z","id":23580,"payee_acc_id":13297,"payer_acc_id":113333,"txn_amt":196.2,"txn_type":2}
{"currency":"USD","datetime":"2022-08-13T18:35:19.000Z","id":23587,"payee_acc_id":5422,"payer_acc_id":113342,"txn_amt":183.57,"txn_type":3}
{"currency":"USD","datetime":"2022-06-24T17:21:43.000Z","id":23593,"payee_acc_id":34975,"payer_acc_id":113365,"txn_amt":80.11,"txn_type":3}
{"currency":"USD","datetime":"2022-01-30T08:49:49.000Z","id":23599,"payee_acc_id":18831,"payer_acc_id":113377,"txn_amt":244.4,"txn_type":2}
{"currency":"USD","datetime":"2022-09-11T00:43:40.000Z","id":23608,"payee_acc_id":22841,"payer_acc_id":113390,"txn_amt":185.0,"txn_type":3}
{"currency":"USD","datetime":"2022-02-22T21:17:43.000Z","id":23611,"payee_acc_id":34752,"payer_acc_id":113404,"txn_amt":76.58,"txn_type":3}
{"currency":"USD","datetime":"2022-09-01T08:24:14.000Z","id":23623,"payee_acc_id":19739,"payer_acc_id":113427,"txn_amt":202.5,"txn_type":4}
{"currency":"USD","datetime":"2022-02-24T13:59:52.000Z","id":23624,"payee_acc_id":31170,"payer_acc_id":113429,"txn_amt":176.1,"txn_type":5}
{"currency":"USD","datetime":"2022-08-07T20:57:59.000Z","id":23626,"payee_acc_id":1788,"payer_acc_id":113432,"txn_amt":255.42,"txn_type":1}
{"currency":"USD","datetime":"2022-06-10T21:33:24.000Z","id":23637,"payee_acc_id":5644,"payer_acc_id":113449,"txn_amt":165.47,"txn_type":3}
{"currency":"USD","datetime":"2022-02-13T21:30:23.000Z","id":23638,"payee_acc_id":4797,"payer_acc_id":113450,"txn_amt":178.33,"txn_type":4}
{"currency":"USD","datetime":"2022-02-08T10:49:13.000Z","id":2364,"payee_acc_id":139349,"payer_acc_id":79696,"txn_amt":209.09,"txn_type":1}
{"currency":"USD","datetime":"2022-11-27T02:31:27.000Z","id":23642,"payee_acc_id":4058,"payer_acc_id":113456,"txn_amt":283.95,"txn_type":2}
{"currency":"USD","datetime":"2022-12-01T16:32:23.000Z","id":23643,"payee_acc_id":2550,"payer_acc_id":113457,"txn_amt":150.77,"txn_type":4}
{"currency":"USD","datetime":"2022-12-15T06:16:36.000Z","id":23646,"payee_acc_id":1021,"payer_acc_id":113463,"txn_amt":281.31,"txn_type":3}
{"currency":"USD","datetime":"2022-11-26T17:40:01.000Z","id":23655,"payee_acc_id":8039,"payer_acc_id":113477,"txn_amt":199.62,"txn_type":5}
{"currency":"USD","datetime":"2022-12-24T05:12:21.000Z","id":23669,"payee_acc_id":2994,"payer_acc_id":113495,"txn_amt":139.33,"txn_type":3}
{"currency":"USD","datetime":"2022-02-11T09:58:41.000Z","id":23671,"payee_acc_id":7674,"payer_acc_id":113498,"txn_amt":172.96,"txn_type":5}
{"currency":"USD","datetime":"2022-09-06T21:46:06.000Z","id":23675,"payee_acc_id":10576,"payer_acc_id":113504,"txn_amt":209.2,"txn_type":1}
{"currency":"USD","datetime":"2022-10-10T03:50:08.000Z","id":23679,"payee_acc_id":6099,"payer_acc_id":113505,"txn_amt":181.07,"txn_type":1}
{"currency":"USD","datetime":"2022-05-22T10:24:19.000Z","id":23687,"payee_acc_id":5649,"payer_acc_id":113515,"txn_amt":157.57,"txn_type":5}
